odoo9_addon_l10n_et_base-9.0.1.0.0-py2.7-nspkg.pth
odoo_addons/l10n_et_base/__openerp__.py
odoo_addons/l10n_et_base/res_view.xml
odoo_addons/l10n_et_base/__init__.py
odoo_addons/l10n_et_base/README.rst
odoo_addons/l10n_et_base/res.py
odoo_addons/l10n_et_base/models/res_partner.py
odoo_addons/l10n_et_base/models/__init__.py
odoo_addons/l10n_et_base/models/res_company.py
odoo_addons/l10n_et_base/models/res_country.py
odoo_addons/l10n_et_base/views/res_partner.xml
odoo_addons/l10n_et_base/views/res_company.xml
odoo_addons/l10n_et_base/static/description/icon.png
odoo9_addon_l10n_et_base-9.0.1.0.0.dist-info/top_level.txt
odoo9_addon_l10n_et_base-9.0.1.0.0.dist-info/WHEEL
odoo9_addon_l10n_et_base-9.0.1.0.0.dist-info/RECORD
odoo9_addon_l10n_et_base-9.0.1.0.0.dist-info/metadata.json
odoo9_addon_l10n_et_base-9.0.1.0.0.dist-info/DESCRIPTION.rst
odoo9_addon_l10n_et_base-9.0.1.0.0.dist-info/METADATA
odoo9_addon_l10n_et_base-9.0.1.0.0.dist-info/namespace_packages.txt
